{"zip":"035","pref":"青森県","data": {
"0000":"下北郡東通村",
"0001":"下北郡東通村大利",
"0002":"下北郡東通村目名",
"0003":"下北郡東通村野牛",
"0004":"下北郡東通村蒲野沢",
"0005":"下北郡東通村田屋",
"0011":"むつ市奥内",
"0012":"むつ市中野沢",
"0021":"むつ市田名部",
"0022":"むつ市関根",
"0031":"むつ市柳町",
"0032":"むつ市上川町",
"0033":"むつ市横迎町",
"0034":"むつ市田名部町",
"0035":"むつ市本町",
"0036":"むつ市栗山町",
"0041":"むつ市金曲",
"0042":"むつ市大曲",
"0043":"むつ市南赤川町",
"0044":"むつ市赤川町",
"0045":"むつ市松原町",
"0046":"むつ市南町",
"0051":"むつ市新町",
"0052":"むつ市昭和町",
"0053":"むつ市緑町",
"0054":"むつ市海老川町",
"0055":"むつ市苫生町",
"0061":"むつ市下北町",
"0062":"むつ市仲町",
"0063":"むつ市若松町",
"0064":"むつ市港町",
"0065":"むつ市松山町",
"0066":"むつ市緑ヶ丘",
"0067":"むつ市十二林",
"0068":"むつ市美里町",
"0071":"むつ市小川町",
"0072":"むつ市金谷",
"0073":"むつ市中央",
"0074":"むつ市大平",
"0075":"むつ市真砂町",
"0076":"むつ市旭町",
"0077":"むつ市山田町",
"0078":"むつ市松森町",
"0079":"むつ市荒川町",
"0081":"むつ市並川町",
"0082":"むつ市文京町",
"0083":"むつ市大平町",
"0084":"むつ市大湊新町",
"0085":"むつ市大湊浜町",
"0086":"むつ市大湊上町",
"0091":"むつ市川守町",
"0092":"むつ市宇田町",
"0093":"むつ市大湊町",
"0094":"むつ市桜木町",
"0095":"むつ市城ケ沢",
"0096":"むつ市大湊",
"0103":"下北郡東通村野牛",
"0104":"下北郡東通村蒲野沢",
"0111":"下北郡東通村尻屋",
"0112":"下北郡東通村尻労",
"0113":"下北郡東通村岩屋"
}}
