{"zip":"163","pref":"東京都","data": {
"0201":"新宿区西新宿新宿住友ビル",
"0202":"新宿区西新宿新宿住友ビル",
"0203":"新宿区西新宿新宿住友ビル",
"0204":"新宿区西新宿新宿住友ビル",
"0205":"新宿区西新宿新宿住友ビル",
"0206":"新宿区西新宿新宿住友ビル",
"0207":"新宿区西新宿新宿住友ビル",
"0208":"新宿区西新宿新宿住友ビル",
"0209":"新宿区西新宿新宿住友ビル",
"0210":"新宿区西新宿新宿住友ビル",
"0211":"新宿区西新宿新宿住友ビル",
"0212":"新宿区西新宿新宿住友ビル",
"0213":"新宿区西新宿新宿住友ビル",
"0214":"新宿区西新宿新宿住友ビル",
"0215":"新宿区西新宿新宿住友ビル",
"0216":"新宿区西新宿新宿住友ビル",
"0217":"新宿区西新宿新宿住友ビル",
"0218":"新宿区西新宿新宿住友ビル",
"0219":"新宿区西新宿新宿住友ビル",
"0220":"新宿区西新宿新宿住友ビル",
"0221":"新宿区西新宿新宿住友ビル",
"0222":"新宿区西新宿新宿住友ビル",
"0223":"新宿区西新宿新宿住友ビル",
"0224":"新宿区西新宿新宿住友ビル",
"0225":"新宿区西新宿新宿住友ビル",
"0226":"新宿区西新宿新宿住友ビル",
"0227":"新宿区西新宿新宿住友ビル",
"0228":"新宿区西新宿新宿住友ビル",
"0229":"新宿区西新宿新宿住友ビル",
"0230":"新宿区西新宿新宿住友ビル",
"0231":"新宿区西新宿新宿住友ビル",
"0232":"新宿区西新宿新宿住友ビル",
"0233":"新宿区西新宿新宿住友ビル",
"0234":"新宿区西新宿新宿住友ビル",
"0235":"新宿区西新宿新宿住友ビル",
"0236":"新宿区西新宿新宿住友ビル",
"0237":"新宿区西新宿新宿住友ビル",
"0238":"新宿区西新宿新宿住友ビル",
"0239":"新宿区西新宿新宿住友ビル",
"0240":"新宿区西新宿新宿住友ビル",
"0241":"新宿区西新宿新宿住友ビル",
"0242":"新宿区西新宿新宿住友ビル",
"0243":"新宿区西新宿新宿住友ビル",
"0244":"新宿区西新宿新宿住友ビル",
"0245":"新宿区西新宿新宿住友ビル",
"0246":"新宿区西新宿新宿住友ビル",
"0247":"新宿区西新宿新宿住友ビル",
"0248":"新宿区西新宿新宿住友ビル",
"0249":"新宿区西新宿新宿住友ビル",
"0250":"新宿区西新宿新宿住友ビル",
"0251":"新宿区西新宿新宿住友ビル",
"0252":"新宿区西新宿新宿住友ビル",
"0290":"新宿区西新宿新宿住友ビル",
"0401":"新宿区西新宿新宿三井ビル",
"0402":"新宿区西新宿新宿三井ビル",
"0403":"新宿区西新宿新宿三井ビル",
"0404":"新宿区西新宿新宿三井ビル",
"0405":"新宿区西新宿新宿三井ビル",
"0406":"新宿区西新宿新宿三井ビル",
"0407":"新宿区西新宿新宿三井ビル",
"0408":"新宿区西新宿新宿三井ビル",
"0409":"新宿区西新宿新宿三井ビル",
"0410":"新宿区西新宿新宿三井ビル",
"0411":"新宿区西新宿新宿三井ビル",
"0412":"新宿区西新宿新宿三井ビル",
"0413":"新宿区西新宿新宿三井ビル",
"0414":"新宿区西新宿新宿三井ビル",
"0415":"新宿区西新宿新宿三井ビル",
"0416":"新宿区西新宿新宿三井ビル",
"0417":"新宿区西新宿新宿三井ビル",
"0418":"新宿区西新宿新宿三井ビル",
"0419":"新宿区西新宿新宿三井ビル",
"0420":"新宿区西新宿新宿三井ビル",
"0421":"新宿区西新宿新宿三井ビル",
"0422":"新宿区西新宿新宿三井ビル",
"0423":"新宿区西新宿新宿三井ビル",
"0424":"新宿区西新宿新宿三井ビル",
"0425":"新宿区西新宿新宿三井ビル",
"0426":"新宿区西新宿新宿三井ビル",
"0427":"新宿区西新宿新宿三井ビル",
"0428":"新宿区西新宿新宿三井ビル",
"0429":"新宿区西新宿新宿三井ビル",
"0430":"新宿区西新宿新宿三井ビル",
"0431":"新宿区西新宿新宿三井ビル",
"0432":"新宿区西新宿新宿三井ビル",
"0433":"新宿区西新宿新宿三井ビル",
"0434":"新宿区西新宿新宿三井ビル",
"0435":"新宿区西新宿新宿三井ビル",
"0436":"新宿区西新宿新宿三井ビル",
"0437":"新宿区西新宿新宿三井ビル",
"0438":"新宿区西新宿新宿三井ビル",
"0439":"新宿区西新宿新宿三井ビル",
"0440":"新宿区西新宿新宿三井ビル",
"0441":"新宿区西新宿新宿三井ビル",
"0442":"新宿区西新宿新宿三井ビル",
"0443":"新宿区西新宿新宿三井ビル",
"0444":"新宿区西新宿新宿三井ビル",
"0445":"新宿区西新宿新宿三井ビル",
"0446":"新宿区西新宿新宿三井ビル",
"0447":"新宿区西新宿新宿三井ビル",
"0448":"新宿区西新宿新宿三井ビル",
"0449":"新宿区西新宿新宿三井ビル",
"0450":"新宿区西新宿新宿三井ビル",
"0451":"新宿区西新宿新宿三井ビル",
"0452":"新宿区西新宿新宿三井ビル",
"0453":"新宿区西新宿新宿三井ビル",
"0454":"新宿区西新宿新宿三井ビル",
"0455":"新宿区西新宿新宿三井ビル",
"0490":"新宿区西新宿新宿三井ビル",
"0501":"新宿区西新宿新宿野村ビル",
"0502":"新宿区西新宿新宿野村ビル",
"0503":"新宿区西新宿新宿野村ビル",
"0504":"新宿区西新宿新宿野村ビル",
"0505":"新宿区西新宿新宿野村ビル",
"0506":"新宿区西新宿新宿野村ビル",
"0507":"新宿区西新宿新宿野村ビル",
"0508":"新宿区西新宿新宿野村ビル",
"0509":"新宿区西新宿新宿野村ビル",
"0510":"新宿区西新宿新宿野村ビル",
"0511":"新宿区西新宿新宿野村ビル",
"0512":"新宿区西新宿新宿野村ビル",
"0513":"新宿区西新宿新宿野村ビル",
"0514":"新宿区西新宿新宿野村ビル",
"0515":"新宿区西新宿新宿野村ビル",
"0516":"新宿区西新宿新宿野村ビル",
"0517":"新宿区西新宿新宿野村ビル",
"0518":"新宿区西新宿新宿野村ビル",
"0519":"新宿区西新宿新宿野村ビル",
"0520":"新宿区西新宿新宿野村ビル",
"0521":"新宿区西新宿新宿野村ビル",
"0522":"新宿区西新宿新宿野村ビル",
"0523":"新宿区西新宿新宿野村ビル",
"0524":"新宿区西新宿新宿野村ビル",
"0525":"新宿区西新宿新宿野村ビル",
"0526":"新宿区西新宿新宿野村ビル",
"0527":"新宿区西新宿新宿野村ビル",
"0528":"新宿区西新宿新宿野村ビル",
"0529":"新宿区西新宿新宿野村ビル",
"0530":"新宿区西新宿新宿野村ビル",
"0531":"新宿区西新宿新宿野村ビル",
"0532":"新宿区西新宿新宿野村ビル",
"0533":"新宿区西新宿新宿野村ビル",
"0534":"新宿区西新宿新宿野村ビル",
"0535":"新宿区西新宿新宿野村ビル",
"0536":"新宿区西新宿新宿野村ビル",
"0537":"新宿区西新宿新宿野村ビル",
"0538":"新宿区西新宿新宿野村ビル",
"0539":"新宿区西新宿新宿野村ビル",
"0540":"新宿区西新宿新宿野村ビル",
"0541":"新宿区西新宿新宿野村ビル",
"0542":"新宿区西新宿新宿野村ビル",
"0543":"新宿区西新宿新宿野村ビル",
"0544":"新宿区西新宿新宿野村ビル",
"0545":"新宿区西新宿新宿野村ビル",
"0546":"新宿区西新宿新宿野村ビル",
"0547":"新宿区西新宿新宿野村ビル",
"0548":"新宿区西新宿新宿野村ビル",
"0549":"新宿区西新宿新宿野村ビル",
"0550":"新宿区西新宿新宿野村ビル",
"0590":"新宿区西新宿新宿野村ビル",
"0601":"新宿区西新宿新宿センタービル",
"0602":"新宿区西新宿新宿センタービル",
"0603":"新宿区西新宿新宿センタービル",
"0604":"新宿区西新宿新宿センタービル",
"0605":"新宿区西新宿新宿センタービル",
"0606":"新宿区西新宿新宿センタービル",
"0607":"新宿区西新宿新宿センタービル",
"0608":"新宿区西新宿新宿センタービル",
"0609":"新宿区西新宿新宿センタービル",
"0610":"新宿区西新宿新宿センタービル",
"0611":"新宿区西新宿新宿センタービル",
"0612":"新宿区西新宿新宿センタービル",
"0613":"新宿区西新宿新宿センタービル",
"0614":"新宿区西新宿新宿センタービル",
"0615":"新宿区西新宿新宿センタービル",
"0616":"新宿区西新宿新宿センタービル",
"0617":"新宿区西新宿新宿センタービル",
"0618":"新宿区西新宿新宿センタービル",
"0619":"新宿区西新宿新宿センタービル",
"0620":"新宿区西新宿新宿センタービル",
"0621":"新宿区西新宿新宿センタービル",
"0622":"新宿区西新宿新宿センタービル",
"0623":"新宿区西新宿新宿センタービル",
"0624":"新宿区西新宿新宿センタービル",
"0625":"新宿区西新宿新宿センタービル",
"0626":"新宿区西新宿新宿センタービル",
"0627":"新宿区西新宿新宿センタービル",
"0628":"新宿区西新宿新宿センタービル",
"0629":"新宿区西新宿新宿センタービル",
"0630":"新宿区西新宿新宿センタービル",
"0631":"新宿区西新宿新宿センタービル",
"0632":"新宿区西新宿新宿センタービル",
"0633":"新宿区西新宿新宿センタービル",
"0634":"新宿区西新宿新宿センタービル",
"0635":"新宿区西新宿新宿センタービル",
"0636":"新宿区西新宿新宿センタービル",
"0637":"新宿区西新宿新宿センタービル",
"0638":"新宿区西新宿新宿センタービル",
"0639":"新宿区西新宿新宿センタービル",
"0640":"新宿区西新宿新宿センタービル",
"0641":"新宿区西新宿新宿センタービル",
"0642":"新宿区西新宿新宿センタービル",
"0643":"新宿区西新宿新宿センタービル",
"0644":"新宿区西新宿新宿センタービル",
"0645":"新宿区西新宿新宿センタービル",
"0646":"新宿区西新宿新宿センタービル",
"0647":"新宿区西新宿新宿センタービル",
"0648":"新宿区西新宿新宿センタービル",
"0649":"新宿区西新宿新宿センタービル",
"0650":"新宿区西新宿新宿センタービル",
"0651":"新宿区西新宿新宿センタービル",
"0652":"新宿区西新宿新宿センタービル",
"0653":"新宿区西新宿新宿センタービル",
"0654":"新宿区西新宿新宿センタービル",
"0690":"新宿区西新宿新宿センタービル",
"0701":"新宿区西新宿新宿第一生命ビルディング",
"0702":"新宿区西新宿新宿第一生命ビルディング",
"0703":"新宿区西新宿新宿第一生命ビルディング",
"0704":"新宿区西新宿新宿第一生命ビルディング",
"0705":"新宿区西新宿新宿第一生命ビルディング",
"0706":"新宿区西新宿新宿第一生命ビルディング",
"0707":"新宿区西新宿新宿第一生命ビルディング",
"0708":"新宿区西新宿新宿第一生命ビルディング",
"0709":"新宿区西新宿新宿第一生命ビルディング",
"0710":"新宿区西新宿新宿第一生命ビルディング",
"0711":"新宿区西新宿新宿第一生命ビルディング",
"0712":"新宿区西新宿新宿第一生命ビルディング",
"0713":"新宿区西新宿新宿第一生命ビルディング",
"0714":"新宿区西新宿新宿第一生命ビルディング",
"0715":"新宿区西新宿新宿第一生命ビルディング",
"0716":"新宿区西新宿新宿第一生命ビルディング",
"0717":"新宿区西新宿新宿第一生命ビルディング",
"0718":"新宿区西新宿新宿第一生命ビルディング",
"0719":"新宿区西新宿新宿第一生命ビルディング",
"0720":"新宿区西新宿新宿第一生命ビルディング",
"0721":"新宿区西新宿新宿第一生命ビルディング",
"0722":"新宿区西新宿新宿第一生命ビルディング",
"0723":"新宿区西新宿新宿第一生命ビルディング",
"0724":"新宿区西新宿新宿第一生命ビルディング",
"0725":"新宿区西新宿新宿第一生命ビルディング",
"0726":"新宿区西新宿新宿第一生命ビルディング",
"0790":"新宿区西新宿新宿第一生命ビルディング",
"0801":"新宿区西新宿新宿ＮＳビル",
"0802":"新宿区西新宿新宿ＮＳビル",
"0803":"新宿区西新宿新宿ＮＳビル",
"0804":"新宿区西新宿新宿ＮＳビル",
"0805":"新宿区西新宿新宿ＮＳビル",
"0806":"新宿区西新宿新宿ＮＳビル",
"0807":"新宿区西新宿新宿ＮＳビル",
"0808":"新宿区西新宿新宿ＮＳビル",
"0809":"新宿区西新宿新宿ＮＳビル",
"0810":"新宿区西新宿新宿ＮＳビル",
"0811":"新宿区西新宿新宿ＮＳビル",
"0812":"新宿区西新宿新宿ＮＳビル",
"0813":"新宿区西新宿新宿ＮＳビル",
"0814":"新宿区西新宿新宿ＮＳビル",
"0815":"新宿区西新宿新宿ＮＳビル",
"0816":"新宿区西新宿新宿ＮＳビル",
"0817":"新宿区西新宿新宿ＮＳビル",
"0818":"新宿区西新宿新宿ＮＳビル",
"0819":"新宿区西新宿新宿ＮＳビル",
"0820":"新宿区西新宿新宿ＮＳビル",
"0821":"新宿区西新宿新宿ＮＳビル",
"0822":"新宿区西新宿新宿ＮＳビル",
"0823":"新宿区西新宿新宿ＮＳビル",
"0824":"新宿区西新宿新宿ＮＳビル",
"0825":"新宿区西新宿新宿ＮＳビル",
"0826":"新宿区西新宿新宿ＮＳビル",
"0827":"新宿区西新宿新宿ＮＳビル",
"0828":"新宿区西新宿新宿ＮＳビル",
"0829":"新宿区西新宿新宿ＮＳビル",
"0830":"新宿区西新宿新宿ＮＳビル",
"0890":"新宿区西新宿新宿ＮＳビル",
"0901":"新宿区西新宿新宿モノリス",
"0902":"新宿区西新宿新宿モノリス",
"0903":"新宿区西新宿新宿モノリス",
"0904":"新宿区西新宿新宿モノリス",
"0905":"新宿区西新宿新宿モノリス",
"0906":"新宿区西新宿新宿モノリス",
"0907":"新宿区西新宿新宿モノリス",
"0908":"新宿区西新宿新宿モノリス",
"0909":"新宿区西新宿新宿モノリス",
"0910":"新宿区西新宿新宿モノリス",
"0911":"新宿区西新宿新宿モノリス",
"0912":"新宿区西新宿新宿モノリス",
"0913":"新宿区西新宿新宿モノリス",
"0914":"新宿区西新宿新宿モノリス",
"0915":"新宿区西新宿新宿モノリス",
"0916":"新宿区西新宿新宿モノリス",
"0917":"新宿区西新宿新宿モノリス",
"0918":"新宿区西新宿新宿モノリス",
"0919":"新宿区西新宿新宿モノリス",
"0920":"新宿区西新宿新宿モノリス",
"0921":"新宿区西新宿新宿モノリス",
"0922":"新宿区西新宿新宿モノリス",
"0923":"新宿区西新宿新宿モノリス",
"0924":"新宿区西新宿新宿モノリス",
"0925":"新宿区西新宿新宿モノリス",
"0926":"新宿区西新宿新宿モノリス",
"0927":"新宿区西新宿新宿モノリス",
"0928":"新宿区西新宿新宿モノリス",
"0929":"新宿区西新宿新宿モノリス",
"0930":"新宿区西新宿新宿モノリス",
"0990":"新宿区西新宿新宿モノリス",
"1001":"新宿区西新宿新宿パークタワー",
"1002":"新宿区西新宿新宿パークタワー",
"1003":"新宿区西新宿新宿パークタワー",
"1004":"新宿区西新宿新宿パークタワー",
"1005":"新宿区西新宿新宿パークタワー",
"1006":"新宿区西新宿新宿パークタワー",
"1007":"新宿区西新宿新宿パークタワー",
"1008":"新宿区西新宿新宿パークタワー",
"1009":"新宿区西新宿新宿パークタワー",
"1010":"新宿区西新宿新宿パークタワー",
"1011":"新宿区西新宿新宿パークタワー",
"1012":"新宿区西新宿新宿パークタワー",
"1013":"新宿区西新宿新宿パークタワー",
"1014":"新宿区西新宿新宿パークタワー",
"1015":"新宿区西新宿新宿パークタワー",
"1016":"新宿区西新宿新宿パークタワー",
"1017":"新宿区西新宿新宿パークタワー",
"1018":"新宿区西新宿新宿パークタワー",
"1019":"新宿区西新宿新宿パークタワー",
"1020":"新宿区西新宿新宿パークタワー",
"1021":"新宿区西新宿新宿パークタワー",
"1022":"新宿区西新宿新宿パークタワー",
"1023":"新宿区西新宿新宿パークタワー",
"1024":"新宿区西新宿新宿パークタワー",
"1025":"新宿区西新宿新宿パークタワー",
"1026":"新宿区西新宿新宿パークタワー",
"1027":"新宿区西新宿新宿パークタワー",
"1028":"新宿区西新宿新宿パークタワー",
"1029":"新宿区西新宿新宿パークタワー",
"1030":"新宿区西新宿新宿パークタワー",
"1031":"新宿区西新宿新宿パークタワー",
"1032":"新宿区西新宿新宿パークタワー",
"1033":"新宿区西新宿新宿パークタワー",
"1034":"新宿区西新宿新宿パークタワー",
"1035":"新宿区西新宿新宿パークタワー",
"1036":"新宿区西新宿新宿パークタワー",
"1037":"新宿区西新宿新宿パークタワー",
"1038":"新宿区西新宿新宿パークタワー",
"1039":"新宿区西新宿新宿パークタワー",
"1040":"新宿区西新宿新宿パークタワー",
"1041":"新宿区西新宿新宿パークタワー",
"1042":"新宿区西新宿新宿パークタワー",
"1043":"新宿区西新宿新宿パークタワー",
"1044":"新宿区西新宿新宿パークタワー",
"1045":"新宿区西新宿新宿パークタワー",
"1046":"新宿区西新宿新宿パークタワー",
"1047":"新宿区西新宿新宿パークタワー",
"1048":"新宿区西新宿新宿パークタワー",
"1049":"新宿区西新宿新宿パークタワー",
"1050":"新宿区西新宿新宿パークタワー",
"1051":"新宿区西新宿新宿パークタワー",
"1052":"新宿区西新宿新宿パークタワー",
"1090":"新宿区西新宿新宿パークタワー",
"1101":"新宿区西新宿新宿スクエアタワー",
"1102":"新宿区西新宿新宿スクエアタワー",
"1103":"新宿区西新宿新宿スクエアタワー",
"1104":"新宿区西新宿新宿スクエアタワー",
"1105":"新宿区西新宿新宿スクエアタワー",
"1106":"新宿区西新宿新宿スクエアタワー",
"1107":"新宿区西新宿新宿スクエアタワー",
"1108":"新宿区西新宿新宿スクエアタワー",
"1109":"新宿区西新宿新宿スクエアタワー",
"1110":"新宿区西新宿新宿スクエアタワー",
"1111":"新宿区西新宿新宿スクエアタワー",
"1112":"新宿区西新宿新宿スクエアタワー",
"1113":"新宿区西新宿新宿スクエアタワー",
"1114":"新宿区西新宿新宿スクエアタワー",
"1115":"新宿区西新宿新宿スクエアタワー",
"1116":"新宿区西新宿新宿スクエアタワー",
"1117":"新宿区西新宿新宿スクエアタワー",
"1118":"新宿区西新宿新宿スクエアタワー",
"1119":"新宿区西新宿新宿スクエアタワー",
"1120":"新宿区西新宿新宿スクエアタワー",
"1121":"新宿区西新宿新宿スクエアタワー",
"1122":"新宿区西新宿新宿スクエアタワー",
"1123":"新宿区西新宿新宿スクエアタワー",
"1124":"新宿区西新宿新宿スクエアタワー",
"1125":"新宿区西新宿新宿スクエアタワー",
"1126":"新宿区西新宿新宿スクエアタワー",
"1127":"新宿区西新宿新宿スクエアタワー",
"1128":"新宿区西新宿新宿スクエアタワー",
"1129":"新宿区西新宿新宿スクエアタワー",
"1130":"新宿区西新宿新宿スクエアタワー",
"1190":"新宿区西新宿新宿スクエアタワー",
"1301":"新宿区西新宿新宿アイランドタワー",
"1302":"新宿区西新宿新宿アイランドタワー",
"1303":"新宿区西新宿新宿アイランドタワー",
"1304":"新宿区西新宿新宿アイランドタワー",
"1305":"新宿区西新宿新宿アイランドタワー",
"1306":"新宿区西新宿新宿アイランドタワー",
"1307":"新宿区西新宿新宿アイランドタワー",
"1308":"新宿区西新宿新宿アイランドタワー",
"1309":"新宿区西新宿新宿アイランドタワー",
"1310":"新宿区西新宿新宿アイランドタワー",
"1311":"新宿区西新宿新宿アイランドタワー",
"1312":"新宿区西新宿新宿アイランドタワー",
"1313":"新宿区西新宿新宿アイランドタワー",
"1314":"新宿区西新宿新宿アイランドタワー",
"1315":"新宿区西新宿新宿アイランドタワー",
"1316":"新宿区西新宿新宿アイランドタワー",
"1317":"新宿区西新宿新宿アイランドタワー",
"1318":"新宿区西新宿新宿アイランドタワー",
"1319":"新宿区西新宿新宿アイランドタワー",
"1320":"新宿区西新宿新宿アイランドタワー",
"1321":"新宿区西新宿新宿アイランドタワー",
"1322":"新宿区西新宿新宿アイランドタワー",
"1323":"新宿区西新宿新宿アイランドタワー",
"1324":"新宿区西新宿新宿アイランドタワー",
"1325":"新宿区西新宿新宿アイランドタワー",
"1326":"新宿区西新宿新宿アイランドタワー",
"1327":"新宿区西新宿新宿アイランドタワー",
"1328":"新宿区西新宿新宿アイランドタワー",
"1329":"新宿区西新宿新宿アイランドタワー",
"1330":"新宿区西新宿新宿アイランドタワー",
"1331":"新宿区西新宿新宿アイランドタワー",
"1332":"新宿区西新宿新宿アイランドタワー",
"1333":"新宿区西新宿新宿アイランドタワー",
"1334":"新宿区西新宿新宿アイランドタワー",
"1335":"新宿区西新宿新宿アイランドタワー",
"1336":"新宿区西新宿新宿アイランドタワー",
"1337":"新宿区西新宿新宿アイランドタワー",
"1338":"新宿区西新宿新宿アイランドタワー",
"1339":"新宿区西新宿新宿アイランドタワー",
"1340":"新宿区西新宿新宿アイランドタワー",
"1341":"新宿区西新宿新宿アイランドタワー",
"1342":"新宿区西新宿新宿アイランドタワー",
"1343":"新宿区西新宿新宿アイランドタワー",
"1344":"新宿区西新宿新宿アイランドタワー",
"1390":"新宿区西新宿新宿アイランドタワー",
"1401":"新宿区西新宿東京オペラシティ",
"1402":"新宿区西新宿東京オペラシティ",
"1403":"新宿区西新宿東京オペラシティ",
"1404":"新宿区西新宿東京オペラシティ",
"1405":"新宿区西新宿東京オペラシティ",
"1406":"新宿区西新宿東京オペラシティ",
"1407":"新宿区西新宿東京オペラシティ",
"1408":"新宿区西新宿東京オペラシティ",
"1409":"新宿区西新宿東京オペラシティ",
"1410":"新宿区西新宿東京オペラシティ",
"1411":"新宿区西新宿東京オペラシティ",
"1412":"新宿区西新宿東京オペラシティ",
"1413":"新宿区西新宿東京オペラシティ",
"1414":"新宿区西新宿東京オペラシティ",
"1415":"新宿区西新宿東京オペラシティ",
"1416":"新宿区西新宿東京オペラシティ",
"1417":"新宿区西新宿東京オペラシティ",
"1418":"新宿区西新宿東京オペラシティ",
"1419":"新宿区西新宿東京オペラシティ",
"1420":"新宿区西新宿東京オペラシティ",
"1421":"新宿区西新宿東京オペラシティ",
"1422":"新宿区西新宿東京オペラシティ",
"1423":"新宿区西新宿東京オペラシティ",
"1424":"新宿区西新宿東京オペラシティ",
"1425":"新宿区西新宿東京オペラシティ",
"1426":"新宿区西新宿東京オペラシティ",
"1427":"新宿区西新宿東京オペラシティ",
"1428":"新宿区西新宿東京オペラシティ",
"1429":"新宿区西新宿東京オペラシティ",
"1430":"新宿区西新宿東京オペラシティ",
"1431":"新宿区西新宿東京オペラシティ",
"1432":"新宿区西新宿東京オペラシティ",
"1433":"新宿区西新宿東京オペラシティ",
"1434":"新宿区西新宿東京オペラシティ",
"1435":"新宿区西新宿東京オペラシティ",
"1436":"新宿区西新宿東京オペラシティ",
"1437":"新宿区西新宿東京オペラシティ",
"1438":"新宿区西新宿東京オペラシティ",
"1439":"新宿区西新宿東京オペラシティ",
"1440":"新宿区西新宿東京オペラシティ",
"1441":"新宿区西新宿東京オペラシティ",
"1442":"新宿区西新宿東京オペラシティ",
"1443":"新宿区西新宿東京オペラシティ",
"1444":"新宿区西新宿東京オペラシティ",
"1445":"新宿区西新宿東京オペラシティ",
"1446":"新宿区西新宿東京オペラシティ",
"1447":"新宿区西新宿東京オペラシティ",
"1448":"新宿区西新宿東京オペラシティ",
"1449":"新宿区西新宿東京オペラシティ",
"1450":"新宿区西新宿東京オペラシティ",
"1451":"新宿区西新宿東京オペラシティ",
"1452":"新宿区西新宿東京オペラシティ",
"1453":"新宿区西新宿東京オペラシティ",
"1454":"新宿区西新宿東京オペラシティ",
"1490":"新宿区西新宿東京オペラシティ",
"1501":"新宿区西新宿新宿エルタワー",
"1502":"新宿区西新宿新宿エルタワー",
"1503":"新宿区西新宿新宿エルタワー",
"1504":"新宿区西新宿新宿エルタワー",
"1505":"新宿区西新宿新宿エルタワー",
"1506":"新宿区西新宿新宿エルタワー",
"1507":"新宿区西新宿新宿エルタワー",
"1508":"新宿区西新宿新宿エルタワー",
"1509":"新宿区西新宿新宿エルタワー",
"1510":"新宿区西新宿新宿エルタワー",
"1511":"新宿区西新宿新宿エルタワー",
"1512":"新宿区西新宿新宿エルタワー",
"1513":"新宿区西新宿新宿エルタワー",
"1514":"新宿区西新宿新宿エルタワー",
"1515":"新宿区西新宿新宿エルタワー",
"1516":"新宿区西新宿新宿エルタワー",
"1517":"新宿区西新宿新宿エルタワー",
"1518":"新宿区西新宿新宿エルタワー",
"1519":"新宿区西新宿新宿エルタワー",
"1520":"新宿区西新宿新宿エルタワー",
"1521":"新宿区西新宿新宿エルタワー",
"1522":"新宿区西新宿新宿エルタワー",
"1523":"新宿区西新宿新宿エルタワー",
"1524":"新宿区西新宿新宿エルタワー",
"1525":"新宿区西新宿新宿エルタワー",
"1526":"新宿区西新宿新宿エルタワー",
"1527":"新宿区西新宿新宿エルタワー",
"1528":"新宿区西新宿新宿エルタワー",
"1529":"新宿区西新宿新宿エルタワー",
"1530":"新宿区西新宿新宿エルタワー",
"1531":"新宿区西新宿新宿エルタワー",
"1590":"新宿区西新宿新宿エルタワー",
"6001":"新宿区西新宿住友不動産新宿オークタワー",
"6002":"新宿区西新宿住友不動産新宿オークタワー",
"6003":"新宿区西新宿住友不動産新宿オークタワー",
"6004":"新宿区西新宿住友不動産新宿オークタワー",
"6005":"新宿区西新宿住友不動産新宿オークタワー",
"6006":"新宿区西新宿住友不動産新宿オークタワー",
"6007":"新宿区西新宿住友不動産新宿オークタワー",
"6008":"新宿区西新宿住友不動産新宿オークタワー",
"6009":"新宿区西新宿住友不動産新宿オークタワー",
"6010":"新宿区西新宿住友不動産新宿オークタワー",
"6011":"新宿区西新宿住友不動産新宿オークタワー",
"6012":"新宿区西新宿住友不動産新宿オークタワー",
"6013":"新宿区西新宿住友不動産新宿オークタワー",
"6014":"新宿区西新宿住友不動産新宿オークタワー",
"6015":"新宿区西新宿住友不動産新宿オークタワー",
"6016":"新宿区西新宿住友不動産新宿オークタワー",
"6017":"新宿区西新宿住友不動産新宿オークタワー",
"6018":"新宿区西新宿住友不動産新宿オークタワー",
"6019":"新宿区西新宿住友不動産新宿オークタワー",
"6020":"新宿区西新宿住友不動産新宿オークタワー",
"6021":"新宿区西新宿住友不動産新宿オークタワー",
"6022":"新宿区西新宿住友不動産新宿オークタワー",
"6023":"新宿区西新宿住友不動産新宿オークタワー",
"6024":"新宿区西新宿住友不動産新宿オークタワー",
"6025":"新宿区西新宿住友不動産新宿オークタワー",
"6026":"新宿区西新宿住友不動産新宿オークタワー",
"6027":"新宿区西新宿住友不動産新宿オークタワー",
"6028":"新宿区西新宿住友不動産新宿オークタワー",
"6029":"新宿区西新宿住友不動産新宿オークタワー",
"6030":"新宿区西新宿住友不動産新宿オークタワー",
"6031":"新宿区西新宿住友不動産新宿オークタワー",
"6032":"新宿区西新宿住友不動産新宿オークタワー",
"6033":"新宿区西新宿住友不動産新宿オークタワー",
"6034":"新宿区西新宿住友不動産新宿オークタワー",
"6035":"新宿区西新宿住友不動産新宿オークタワー",
"6036":"新宿区西新宿住友不動産新宿オークタワー",
"6037":"新宿区西新宿住友不動産新宿オークタワー",
"6038":"新宿区西新宿住友不動産新宿オークタワー",
"6090":"新宿区西新宿住友不動産新宿オークタワー"
}}
