{"zip":"260","pref":"千葉県","data": {
"0000":"千葉市中央区",
"0001":"千葉市中央区都町",
"0002":"千葉市中央区旭町",
"0003":"千葉市中央区鶴沢町",
"0004":"千葉市中央区東本町",
"0005":"千葉市中央区道場南",
"0006":"千葉市中央区道場北",
"0007":"千葉市中央区祐光",
"0011":"千葉市中央区亀井町",
"0012":"千葉市中央区本町",
"0013":"千葉市中央区中央",
"0014":"千葉市中央区本千葉町",
"0015":"千葉市中央区富士見",
"0016":"千葉市中央区栄町",
"0017":"千葉市中央区要町",
"0018":"千葉市中央区院内",
"0021":"千葉市中央区新宿",
"0022":"千葉市中央区神明町",
"0023":"千葉市中央区出洲港",
"0024":"千葉市中央区中央港",
"0025":"千葉市中央区問屋町",
"0026":"千葉市中央区千葉港",
"0027":"千葉市中央区新田町",
"0028":"千葉市中央区新町",
"0031":"千葉市中央区新千葉",
"0032":"千葉市中央区登戸",
"0033":"千葉市中央区春日",
"0034":"千葉市中央区汐見丘町",
"0041":"千葉市中央区東千葉",
"0042":"千葉市中央区椿森",
"0044":"千葉市中央区松波",
"0045":"千葉市中央区弁天",
"0801":"千葉市中央区仁戸名町",
"0802":"千葉市中央区川戸町",
"0803":"千葉市中央区花輪町",
"0804":"千葉市中央区赤井町",
"0805":"千葉市中央区宮崎町",
"0806":"千葉市中央区宮崎",
"0807":"千葉市中央区松ケ丘町",
"0808":"千葉市中央区星久喜町",
"0811":"千葉市中央区大森町",
"0812":"千葉市中央区大巌寺町",
"0813":"千葉市中央区生実町",
"0814":"千葉市中央区南生実町",
"0815":"千葉市中央区今井町",
"0816":"千葉市中央区鵜の森町",
"0821":"千葉市中央区若草",
"0822":"千葉市中央区蘇我町",
"0823":"千葉市中央区塩田町",
"0824":"千葉市中央区浜野町",
"0825":"千葉市中央区村田町",
"0826":"千葉市中央区新浜町",
"0831":"千葉市中央区港町",
"0832":"千葉市中央区寒川町",
"0833":"千葉市中央区稲荷町",
"0834":"千葉市中央区今井",
"0835":"千葉市中央区川崎町",
"0841":"千葉市中央区白旗",
"0842":"千葉市中央区南町",
"0843":"千葉市中央区末広",
"0844":"千葉市中央区千葉寺町",
"0851":"千葉市中央区矢作町",
"0852":"千葉市中央区青葉町",
"0853":"千葉市中央区葛城",
"0854":"千葉市中央区長洲",
"0855":"千葉市中央区市場町",
"0856":"千葉市中央区亥鼻",
"0857":"千葉市中央区亀岡町"
}}
