{"zip":"378","pref":"群馬県","data": {
"0000":"沼田市",
"0001":"沼田市戸神町",
"0002":"沼田市横塚町",
"0003":"沼田市上久屋町",
"0004":"沼田市下久屋町",
"0005":"沼田市久屋原町",
"0011":"沼田市上沼須町",
"0012":"沼田市沼須町",
"0013":"沼田市新町",
"0014":"沼田市栄町",
"0015":"沼田市戸鹿野町",
"0016":"沼田市清水町",
"0017":"沼田市坊新田町",
"0018":"沼田市鍛冶町",
"0021":"沼田市岩本町",
"0022":"沼田市屋形原町",
"0023":"沼田市篠尾町",
"0024":"沼田市下川田町",
"0025":"沼田市今井町",
"0026":"沼田市上川田町",
"0031":"沼田市薄根町",
"0032":"沼田市硯田町",
"0033":"沼田市白岩町",
"0034":"沼田市恩田町",
"0035":"沼田市井土上町",
"0041":"沼田市榛名町",
"0042":"沼田市西倉内町",
"0043":"沼田市東倉内町",
"0044":"沼田市下之町",
"0045":"沼田市材木町",
"0046":"沼田市馬喰町",
"0047":"沼田市上之町",
"0048":"沼田市中町",
"0051":"沼田市上原町",
"0052":"沼田市桜町",
"0053":"沼田市東原新町",
"0054":"沼田市西原新町",
"0055":"沼田市柳町",
"0056":"沼田市高橋場町",
"0061":"沼田市岡谷町",
"0062":"沼田市町田町",
"0063":"沼田市下沼田町",
"0064":"沼田市善桂寺町",
"0065":"沼田市堀廻町",
"0066":"沼田市原町",
"0067":"沼田市大釜町",
"0068":"沼田市宇楚井町",
"0071":"沼田市上発知町",
"0072":"沼田市中発知町",
"0073":"沼田市発知新田町",
"0074":"沼田市下発知町",
"0075":"沼田市奈良町",
"0076":"沼田市秋塚町",
"0077":"沼田市石墨町",
"0078":"沼田市佐山町",
"0100":"利根郡川場村",
"0101":"利根郡川場村谷地",
"0102":"利根郡川場村川場湯原",
"0103":"利根郡川場村中野",
"0104":"利根郡川場村太田川",
"0105":"利根郡川場村小田川",
"0111":"利根郡川場村萩室",
"0112":"利根郡川場村立岩",
"0113":"利根郡川場村生品",
"0114":"利根郡川場村天神",
"0115":"利根郡川場村門前",
"0121":"沼田市白沢町高平",
"0122":"沼田市白沢町生枝",
"0123":"沼田市白沢町岩室",
"0124":"沼田市白沢町尾合",
"0125":"沼田市白沢町平出",
"0126":"沼田市白沢町上古語父",
"0127":"沼田市白沢町下古語父",
"0301":"沼田市利根町平川",
"0302":"沼田市利根町千鳥",
"0303":"沼田市利根町追貝",
"0304":"沼田市利根町大楊",
"0305":"沼田市利根町穴原",
"0306":"沼田市利根町日向南郷",
"0307":"沼田市利根町柿平",
"0311":"沼田市利根町小松",
"0312":"沼田市利根町根利",
"0313":"沼田市利根町日影南郷",
"0314":"沼田市利根町青木",
"0315":"沼田市利根町砂川",
"0316":"沼田市利根町二本松",
"0317":"沼田市利根町多那",
"0321":"沼田市利根町高戸谷",
"0322":"沼田市利根町老神",
"0323":"沼田市利根町大原",
"0324":"沼田市利根町園原",
"0325":"沼田市利根町輪組",
"0326":"沼田市利根町石戸新田",
"0400":"利根郡片品村",
"0401":"利根郡片品村須賀川",
"0402":"利根郡片品村御座入",
"0403":"利根郡片品村菅沼",
"0404":"利根郡片品村築地",
"0405":"利根郡片品村下平",
"0406":"利根郡片品村摺淵",
"0407":"利根郡片品村幡谷",
"0408":"利根郡片品村花咲",
"0409":"利根郡片品村針山",
"0411":"利根郡片品村戸倉",
"0412":"利根郡片品村土出",
"0413":"利根郡片品村越本",
"0414":"利根郡片品村東小川",
"0415":"利根郡片品村鎌田"
}}
