{"zip":"485","pref":"愛知県","data": {
"0000":"小牧市",
"0001":"小牧市久保一色東",
"0002":"小牧市葭原",
"0003":"小牧市久保一色",
"0004":"小牧市田県町",
"0005":"小牧市久保本町",
"0006":"小牧市久保新町",
"0007":"小牧市久保一色南",
"0008":"小牧市寺西",
"0009":"小牧市久保",
"0011":"小牧市岩崎",
"0012":"小牧市小牧原新田",
"0013":"小牧市新町",
"0014":"小牧市安田町",
"0015":"小牧市間々",
"0016":"小牧市間々原新田",
"0017":"小牧市岩崎原",
"0021":"小牧市二重堀",
"0022":"小牧市北外山入鹿新田",
"0023":"小牧市北外山",
"0024":"小牧市南外山",
"0025":"小牧市春日寺",
"0026":"小牧市大山",
"0027":"小牧市緑町",
"0028":"小牧市東新町",
"0029":"小牧市中央",
"0031":"小牧市若草町",
"0032":"小牧市掛割町",
"0033":"小牧市郷中",
"0034":"小牧市市之久田",
"0035":"小牧市多気東町",
"0036":"小牧市下小針天神",
"0037":"小牧市小針",
"0039":"小牧市外堀",
"0041":"小牧市小牧",
"0042":"小牧市桜井",
"0043":"小牧市桜井本町",
"0044":"小牧市常普請",
"0045":"小牧市川西",
"0046":"小牧市堀の内",
"0047":"小牧市曙町",
"0048":"小牧市間々本町",
"0049":"小牧市山北町",
"0051":"小牧市下小針中島",
"0052":"小牧市多気中町",
"0053":"小牧市多気南町",
"0054":"小牧市多気西町",
"0055":"小牧市多気北町",
"0056":"小牧市小木南",
"0057":"小牧市小木西",
"0058":"小牧市小木",
"0059":"小牧市小木東",
"0061":"小牧市藤島町向江",
"0062":"小牧市藤島町中島",
"0063":"小牧市藤島町鏡池",
"0064":"小牧市藤島町徳願寺",
"0065":"小牧市藤島町五才田",
"0066":"小牧市藤島町出口",
"0067":"小牧市藤島町居屋敷",
"0068":"小牧市藤島",
"0069":"小牧市藤島町梵天",
"0071":"小牧市弥生町",
"0072":"小牧市元町",
"0073":"小牧市舟津",
"0074":"小牧市新小木",
"0075":"小牧市三ツ渕",
"0076":"小牧市三ツ渕原新田",
"0077":"小牧市西之島",
"0078":"小牧市西島町",
"0081":"小牧市横内",
"0082":"小牧市村中",
"0083":"小牧市村中新町",
"0084":"小牧市入鹿出新田",
"0085":"小牧市河内屋新田",
"0801":"小牧市大山",
"0802":"小牧市大草",
"0803":"小牧市高根",
"0804":"小牧市池之内",
"0805":"小牧市林",
"0806":"小牧市野口",
"0811":"小牧市光ケ丘",
"0812":"小牧市城山",
"0813":"小牧市桃ケ丘",
"0814":"小牧市古雅",
"0815":"小牧市篠岡",
"0821":"小牧市本庄",
"0822":"小牧市上末",
"0823":"小牧市郷西町",
"0824":"小牧市長治町",
"0825":"小牧市下末",
"0826":"小牧市東田中",
"0827":"小牧市文津",
"0828":"小牧市小松寺",
"0829":"小牧市小牧原",
"0831":"小牧市東",
"0832":"小牧市応時"
}}
