{"zip":"521","pref":"滋賀県","data": {
"0000":"米原市",
"0001":"米原市朝妻筑摩",
"0002":"米原市上多良",
"0003":"米原市入江",
"0004":"米原市磯",
"0011":"米原市中多良",
"0012":"米原市米原",
"0013":"米原市梅ケ原",
"0014":"米原市梅ケ原栄",
"0015":"米原市米原西",
"0016":"米原市下多良",
"0021":"米原市河南",
"0022":"米原市樋口",
"0023":"米原市三吉",
"0024":"米原市西坂",
"0025":"米原市番場",
"0031":"米原市一色",
"0032":"米原市枝折",
"0033":"米原市上丹生",
"0034":"米原市下丹生",
"0035":"米原市醒井",
"0061":"米原市長沢",
"0062":"米原市宇賀野",
"0063":"米原市飯",
"0064":"米原市世継",
"0071":"米原市舟崎",
"0072":"米原市顔戸",
"0073":"米原市箕浦",
"0074":"米原市高溝",
"0081":"米原市多和田",
"0082":"米原市能登瀬",
"0083":"米原市新庄",
"0084":"米原市日光寺",
"0091":"米原市岩脇",
"0092":"米原市西円寺",
"0093":"米原市寺倉",
"0201":"米原市長久寺",
"0202":"米原市柏原",
"0203":"米原市清滝",
"0211":"米原市梓河内",
"0212":"米原市本郷",
"0213":"米原市堂谷",
"0214":"米原市大鹿",
"0215":"米原市山室",
"0216":"米原市菅江",
"0217":"米原市北方",
"0218":"米原市志賀谷",
"0219":"米原市加勢野",
"0221":"米原市池下",
"0222":"米原市天満",
"0223":"米原市本市場",
"0224":"米原市夫馬",
"0225":"米原市市場",
"0226":"米原市朝日",
"0227":"米原市烏脇",
"0231":"米原市村居田",
"0232":"米原市坂口",
"0233":"米原市野一色",
"0234":"米原市井之口",
"0235":"米原市小田",
"0236":"米原市間田",
"0241":"米原市西山",
"0242":"米原市長岡",
"0243":"米原市万願寺",
"0244":"米原市大野木",
"0245":"米原市須川",
"0301":"米原市甲津原",
"0302":"米原市曲谷",
"0303":"米原市甲賀",
"0304":"米原市吉槻",
"0305":"米原市上板並",
"0306":"米原市下板並",
"0307":"米原市大久保",
"0308":"米原市小泉",
"0311":"米原市伊吹",
"0312":"米原市上野",
"0313":"米原市弥高",
"0314":"米原市春照",
"0321":"米原市高番",
"0322":"米原市杉沢",
"0323":"米原市村木",
"0324":"米原市大清水",
"0325":"米原市藤川",
"0326":"米原市寺林",
"0327":"米原市上平寺",
"1101":"彦根市石寺町",
"1102":"彦根市下岡部町",
"1103":"彦根市上岡部町",
"1104":"彦根市出路町",
"1105":"彦根市田原町",
"1111":"彦根市稲里町",
"1112":"彦根市金沢町",
"1113":"彦根市稲部町",
"1114":"彦根市彦富町",
"1115":"彦根市金田町",
"1121":"彦根市海瀬町",
"1122":"彦根市三津町",
"1123":"彦根市肥田町",
"1124":"彦根市野良田町",
"1125":"彦根市稲枝町",
"1126":"彦根市服部町",
"1131":"彦根市上稲葉町",
"1132":"彦根市下稲葉町",
"1133":"彦根市本庄町",
"1134":"彦根市田附町",
"1135":"彦根市新海町",
"1136":"彦根市新海浜",
"1141":"彦根市甲崎町",
"1142":"彦根市下西川町",
"1143":"彦根市上西川町",
"1144":"彦根市普光寺町",
"1145":"彦根市南三ツ谷町",
"1146":"彦根市柳川町",
"1147":"彦根市薩摩町",
"1201":"東近江市新宮町",
"1202":"東近江市阿弥陀堂町",
"1203":"東近江市川南町",
"1204":"東近江市小川町",
"1205":"東近江市躰光寺町",
"1211":"東近江市今町",
"1212":"東近江市種町",
"1213":"東近江市神郷町",
"1214":"東近江市長勝寺町",
"1215":"東近江市佐生町",
"1221":"東近江市垣見町",
"1222":"東近江市佐野町",
"1223":"東近江市猪子町",
"1224":"東近江市林町",
"1225":"東近江市山路町",
"1231":"東近江市能登川町",
"1232":"東近江市北須田町",
"1233":"東近江市南須田町",
"1234":"東近江市きぬがさ町",
"1235":"東近江市伊庭町",
"1241":"東近江市乙女浜町",
"1242":"東近江市福堂町",
"1243":"東近江市栗見新田町",
"1244":"東近江市大中町",
"1245":"東近江市栗見出在家町",
"1301":"近江八幡市安土町大中",
"1311":"近江八幡市安土町下豊浦",
"1321":"近江八幡市安土町桑実寺",
"1322":"近江八幡市安土町宮津",
"1331":"近江八幡市安土町石寺",
"1332":"近江八幡市安土町東老蘇",
"1333":"近江八幡市安土町内野",
"1334":"近江八幡市安土町西老蘇",
"1341":"近江八幡市安土町上豊浦",
"1342":"近江八幡市安土町上出",
"1343":"近江八幡市安土町小中",
"1344":"近江八幡市安土町中屋",
"1345":"近江八幡市安土町慈恩寺",
"1346":"近江八幡市安土町香庄",
"1351":"近江八幡市安土町常楽寺"
}}
