{"zip":"524","pref":"滋賀県","data": {
"0000":"守山市",
"0001":"守山市川田町",
"0002":"守山市小島町",
"0003":"守山市中町",
"0004":"守山市笠原町",
"0011":"守山市今市町",
"0012":"守山市播磨田町",
"0013":"守山市下之郷町",
"0014":"守山市石田町",
"0015":"守山市矢島町",
"0016":"守山市荒見町",
"0021":"守山市吉身町",
"0022":"守山市守山町",
"0031":"守山市立入町",
"0032":"守山市岡町",
"0033":"守山市浮気町",
"0034":"守山市千代町",
"0035":"守山市阿村町",
"0036":"守山市伊勢町",
"0037":"守山市梅田町",
"0041":"守山市勝部町",
"0042":"守山市焔魔堂町",
"0043":"守山市二町町",
"0044":"守山市古高町",
"0045":"守山市金森町",
"0046":"守山市今宿町",
"0051":"守山市三宅町",
"0052":"守山市大門町",
"0053":"守山市横江町",
"0054":"守山市大林町",
"0055":"守山市十二里町",
"0061":"守山市赤野井町",
"0062":"守山市杉江町",
"0063":"守山市欲賀町",
"0064":"守山市森川原町",
"0065":"守山市山賀町",
"0101":"守山市今浜町",
"0102":"守山市水保町",
"0103":"守山市洲本町",
"0104":"守山市木浜町",
"0211":"守山市小浜町",
"0212":"守山市服部町",
"0213":"守山市新庄町",
"0214":"守山市立田町",
"0215":"守山市幸津川町",
"0216":"守山市環境学習都市宣言記念公園"
}}
