{"zip":"850","pref":"長崎県","data": {
"0000":"長崎市",
"0001":"長崎市西山",
"0002":"長崎市木場町",
"0003":"長崎市片淵",
"0004":"長崎市下西山町",
"0005":"長崎市西山本町",
"0006":"長崎市上西山町",
"0007":"長崎市立山",
"0011":"長崎市鳴滝",
"0012":"長崎市本河内",
"0013":"長崎市中川",
"0014":"長崎市新中川町",
"0015":"長崎市桜馬場",
"0016":"長崎市夫婦川町",
"0017":"長崎市新大工町",
"0018":"長崎市伊勢町",
"0021":"長崎市炉粕町",
"0022":"長崎市馬町",
"0023":"長崎市出来大工町",
"0024":"長崎市大井手町",
"0025":"長崎市今博多町",
"0026":"長崎市古町",
"0027":"長崎市桶屋町",
"0028":"長崎市勝山町",
"0029":"長崎市八百屋町",
"0031":"長崎市桜町",
"0032":"長崎市興善町",
"0033":"長崎市万才町",
"0034":"長崎市樺島町",
"0035":"長崎市元船町",
"0036":"長崎市五島町",
"0037":"長崎市金屋町",
"0041":"長崎市浜平",
"0042":"長崎市御船蔵町",
"0043":"長崎市八千代町",
"0044":"長崎市天神町",
"0045":"長崎市宝町",
"0046":"長崎市幸町",
"0047":"長崎市銭座町",
"0048":"長崎市上銭座町",
"0051":"長崎市西坂町",
"0052":"長崎市筑後町",
"0053":"長崎市玉園町",
"0054":"長崎市上町",
"0055":"長崎市中町",
"0056":"長崎市恵美須町",
"0057":"長崎市大黒町",
"0058":"長崎市尾上町",
"0061":"長崎市水の浦町",
"0062":"長崎市大谷町",
"0063":"長崎市飽の浦町",
"0064":"長崎市秋月町",
"0065":"長崎市入船町",
"0066":"長崎市大浜町",
"0067":"長崎市小浦町",
"0068":"長崎市福田本町",
"0071":"長崎市塩浜町",
"0072":"長崎市岩瀬道町",
"0073":"長崎市東立神町",
"0074":"長崎市西立神町",
"0075":"長崎市西泊町",
"0076":"長崎市木鉢町",
"0077":"長崎市小瀬戸町",
"0078":"長崎市神ノ島町",
"0079":"長崎市みなと坂",
"0801":"長崎市八幡町",
"0802":"長崎市伊良林",
"0803":"長崎市風頭町",
"0804":"長崎市彦見町",
"0811":"長崎市矢の平",
"0812":"長崎市白木町",
"0813":"長崎市八つ尾町",
"0821":"長崎市高平町",
"0822":"長崎市愛宕",
"0823":"長崎市弥生町",
"0824":"長崎市三景台町",
"0831":"長崎市鍛冶屋町",
"0832":"長崎市油屋町",
"0833":"長崎市東小島町",
"0834":"長崎市上小島",
"0835":"長崎市桜木町",
"0836":"長崎市中小島",
"0837":"長崎市西小島",
"0841":"長崎市銅座町",
"0842":"長崎市新地町",
"0843":"長崎市常盤町",
"0851":"長崎市古川町",
"0852":"長崎市万屋町",
"0853":"長崎市浜町",
"0854":"長崎市銀屋町",
"0855":"長崎市東古川町",
"0861":"長崎市江戸町",
"0862":"長崎市出島町",
"0871":"長崎市麹屋町",
"0872":"長崎市寺町",
"0873":"長崎市諏訪町",
"0874":"長崎市魚の町",
"0875":"長崎市栄町",
"0876":"長崎市賑町",
"0877":"長崎市築町",
"0901":"長崎市本石灰町",
"0902":"長崎市丸山町",
"0903":"長崎市寄合町",
"0904":"長崎市船大工町",
"0905":"長崎市籠町",
"0906":"長崎市館内町",
"0907":"長崎市稲田町",
"0908":"長崎市十人町",
"0909":"長崎市梅香崎町",
"0911":"長崎市東山手町",
"0912":"長崎市中新町",
"0913":"長崎市元町",
"0914":"長崎市日の出町",
"0915":"長崎市東山町",
"0916":"長崎市大浦東町",
"0917":"長崎市下町",
"0918":"長崎市大浦町",
"0921":"長崎市松が枝町",
"0922":"長崎市相生町",
"0923":"長崎市上田町",
"0924":"長崎市出雲",
"0931":"長崎市南山手町",
"0932":"長崎市東琴平",
"0933":"長崎市西琴平町",
"0934":"長崎市小菅町",
"0935":"長崎市古河町",
"0936":"長崎市浪の平町",
"0937":"長崎市小曽根町",
"0941":"長崎市高丘",
"0942":"長崎市南町",
"0943":"長崎市南が丘町",
"0944":"長崎市八景町",
"0945":"長崎市星取",
"0946":"長崎市川上町",
"0947":"長崎市椎の木町",
"0951":"長崎市国分町",
"0952":"長崎市戸町",
"0953":"長崎市上戸町",
"0954":"長崎市新戸町",
"0961":"長崎市小ケ倉町",
"0962":"長崎市新小が倉",
"0963":"長崎市ダイヤランド",
"0964":"長崎市大山町",
"0971":"長崎市磯道町",
"0972":"長崎市古道町",
"0973":"長崎市鹿尾町",
"0974":"長崎市京太郎町",
"0975":"長崎市三和町",
"0976":"長崎市毛井首町",
"0977":"長崎市土井首町",
"0981":"長崎市草住町",
"0982":"長崎市柳田町",
"0983":"長崎市米山町",
"0984":"長崎市鶴見台",
"0985":"長崎市平瀬町",
"0991":"長崎市末石町",
"0992":"長崎市江川町",
"0993":"長崎市八郎岳町",
"0994":"長崎市竿浦町",
"0995":"長崎市平山町",
"0996":"長崎市平山台"
}}
