{"zip":"955","pref":"新潟県","data": {
"0000":"三条市",
"0001":"三条市三貫地新田",
"0002":"三条市柳川新田",
"0003":"三条市柳場新田",
"0004":"三条市須戸新田",
"0011":"三条市白山新田",
"0012":"三条市北野新田",
"0013":"三条市井栗",
"0014":"三条市西潟",
"0015":"三条市三柳",
"0016":"三条市牛ケ島",
"0021":"三条市下保内",
"0022":"三条市みずほ",
"0024":"三条市柳沢",
"0025":"三条市上野原",
"0031":"三条市松ノ木町",
"0032":"三条市東大崎",
"0033":"三条市西大崎",
"0034":"三条市麻布",
"0035":"三条市中新",
"0036":"三条市篭場",
"0041":"三条市三竹",
"0042":"三条市下坂井",
"0043":"三条市北中",
"0044":"三条市田島",
"0045":"三条市一ノ門",
"0046":"三条市興野",
"0047":"三条市東三条",
"0051":"三条市鶴田",
"0053":"三条市北入蔵",
"0054":"三条市大宮新田",
"0055":"三条市塚野目",
"0056":"三条市嘉坪川",
"0057":"三条市新光町",
"0061":"三条市林町",
"0062":"三条市仲之町",
"0063":"三条市神明町",
"0064":"三条市横町",
"0065":"三条市旭町",
"0066":"三条市居島",
"0071":"三条市本町",
"0072":"三条市元町",
"0073":"三条市八幡町",
"0081":"三条市東裏館",
"0082":"三条市西裏館",
"0083":"三条市荒町",
"0084":"三条市石上",
"0085":"三条市栗林",
"0091":"三条市上須頃",
"0092":"三条市須頃",
"0093":"三条市下須頃",
"0094":"三条市大島",
"0095":"三条市代官島",
"0096":"三条市井戸場",
"0097":"三条市荻島",
"0101":"三条市曲谷",
"0102":"三条市牛ケ首",
"0103":"三条市落合",
"0104":"三条市江口",
"0105":"三条市島川原",
"0106":"三条市南中",
"0107":"三条市飯田",
"0108":"三条市鹿峠",
"0111":"三条市上谷地",
"0112":"三条市蝶名林",
"0113":"三条市中浦",
"0114":"三条市鹿熊",
"0115":"三条市院内",
"0116":"三条市森町",
"0117":"三条市田屋",
"0118":"三条市新屋",
"0121":"三条市北五百川",
"0122":"三条市大谷地",
"0123":"三条市笠堀",
"0124":"三条市大谷",
"0125":"三条市塩野渕",
"0126":"三条市栗山",
"0127":"三条市名下",
"0128":"三条市南五百川",
"0131":"三条市庭月",
"0132":"三条市長野",
"0133":"三条市牛野尾",
"0134":"三条市濁沢",
"0135":"三条市早水",
"0136":"三条市葎谷",
"0137":"三条市遅場",
"0141":"三条市荒沢",
"0142":"三条市小長沢",
"0143":"三条市棚鱗",
"0144":"三条市楢山",
"0145":"三条市大沢",
"0146":"三条市笹巻",
"0147":"三条市中野原",
"0148":"三条市花渕",
"0151":"三条市荻堀",
"0152":"三条市笹岡",
"0153":"三条市桑切",
"0154":"三条市大平",
"0155":"三条市広手",
"0156":"三条市駒込",
"0157":"三条市長沢",
"0158":"三条市原",
"0161":"三条市高岡",
"0162":"三条市福岡",
"0163":"三条市島潟",
"0164":"三条市滝谷",
"0165":"三条市高屋敷",
"0166":"三条市上大浦",
"0167":"三条市馬場",
"0168":"三条市下大浦",
"0801":"三条市諏訪",
"0803":"三条市月岡",
"0804":"三条市如法寺",
"0805":"三条市吉田",
"0806":"三条市長嶺",
"0807":"三条市片口",
"0808":"三条市新保",
"0811":"三条市南入蔵",
"0812":"三条市入蔵新田",
"0813":"三条市袋",
"0814":"三条市金子新田",
"0815":"三条市西鱈田",
"0816":"三条市東鱈田",
"0818":"三条市枝郷",
"0821":"三条市五明",
"0822":"三条市西中",
"0823":"三条市東本成寺",
"0824":"三条市下新田",
"0831":"三条市土場",
"0832":"三条市直江町",
"0833":"三条市大野畑",
"0841":"三条市由利",
"0842":"三条市島田",
"0843":"三条市条南町",
"0844":"三条市桜木町",
"0845":"三条市緑ケ丘",
"0851":"三条市西四日町",
"0852":"三条市南四日町",
"0853":"三条市北四日町",
"0854":"三条市四日町",
"0861":"三条市北新保",
"0862":"三条市南新保",
"0863":"三条市東新保",
"0864":"三条市曲渕"
}}
